countless_admin/__init__.py
django_admin_countless-0.4.0.dist-info/LICENSE
django_admin_countless-0.4.0.dist-info/METADATA
django_admin_countless-0.4.0.dist-info/WHEEL
django_admin_countless-0.4.0.dist-info/top_level.txt
django_admin_countless-0.4.0.dist-info/RECORD
